jupyterutils/__init__.py
jupyterutils/_version.py
jupyterutils/prepuller/__init__.py
jupyterutils/prepuller/_version.py
jupyterutils/prepuller/prepuller.py
jupyterutils/prepuller/standalone.py
jupyterutils/scanrepo/__init__.py
jupyterutils/scanrepo/scanrepo.py
jupyterutils/scanrepo/standalone.py
jupyterutils-0.0.4.dist-info/LICENSE
jupyterutils-0.0.4.dist-info/METADATA
jupyterutils-0.0.4.dist-info/WHEEL
jupyterutils-0.0.4.dist-info/entry_points.txt
jupyterutils-0.0.4.dist-info/top_level.txt
jupyterutils-0.0.4.dist-info/RECORD
