Metadata-Version: 2.1
Name: jupyterutils
Version: 0.0.4
Summary: UNKNOWN
Home-page: https://github.com/sqre-lsst/jupyterutils
Author: Adam Thornton
Author-email: athornton@lsst.org
License: MIT
Keywords: lsst
Platform: UNKNOWN
Classifier: Development Status :: 4 - Beta
Classifier: Programming Language :: Python :: 2.7
Classifier: Programming Language :: Python :: 3.5
Classifier: License :: OSI Approved :: MIT License
Requires-Dist: requests (<3.0.0,>=2.0.0)
Requires-Dist: kubernetes (<7.0.0,>=4.0.0)
